belorthography/__init__.py
belorthography/diff_mode.py
belorthography/engine.py
belorthography/orthographies.py
belorthography/converters/__init__.py
belorthography/converters/translit_cyr_nar_to_cyr_taras.py
belorthography/converters/translit_cyr_taras_to_lat.py
belorthography/converters/translit_lat_to_lat_no_diactric.py
belorthography/converters/util.py
belorthography-1.0.0.dist-info/METADATA
belorthography-1.0.0.dist-info/WHEEL
belorthography-1.0.0.dist-info/RECORD
