Metadata-Version: 2.1
Name: belorthography
Version: 1.0.0
Summary: Library for converting Belarusian text to different orthographies (e.g. lacinka).
Project-URL: Homepage, https://github.com/belaudiobooks/belorthography
Project-URL: Bug Tracker, https://github.com/belaudiobooks/belorthography/issues
Author-email: Mikita Belahlazau <nikelandjelo@gmail.com>, Aliaksandr Parfianiuk <frombrest@gmail.com>
Classifier: License :: OSI Approved :: MIT License
Classifier: Operating System :: OS Independent
Classifier: Programming Language :: Python :: 3
Requires-Python: >=3.7
